fields_permissions/__init__.py
fields_permissions/mixins.py
drf_serializer_fields_permissions-0.2.0.dist-info/LICENSE
drf_serializer_fields_permissions-0.2.0.dist-info/METADATA
drf_serializer_fields_permissions-0.2.0.dist-info/WHEEL
drf_serializer_fields_permissions-0.2.0.dist-info/top_level.txt
drf_serializer_fields_permissions-0.2.0.dist-info/RECORD
