Metadata-Version: 2.1
Name: drf_serializer_fields_permissions
Version: 0.2.0
Summary: Permissions for django-rest fields
Home-page: https://github.com/starnavi-team/drf_serializer_fields_permissions
Author: starnavi.io
Author-email: hello@starnavi.io
License: BSD
Classifier: Development Status :: 2 - Pre-Alpha
Classifier: Environment :: Web Environment
Classifier: Framework :: Django
Classifier: Intended Audience :: Developers
Classifier: License :: OSI Approved :: BSD License
Classifier: Operating System :: OS Independent
Classifier: Natural Language :: English
Classifier: Programming Language :: Python :: 3.5
Classifier: Programming Language :: Python :: 3.6
Classifier: Programming Language :: Python :: 3.7
Classifier: Programming Language :: Python :: 3.8
Classifier: Programming Language :: Python :: 3.9
Classifier: Programming Language :: Python :: 3.10
Classifier: Programming Language :: Python :: 3.11
Classifier: Topic :: Internet :: WWW/HTTP
License-File: LICENSE
Requires-Dist: Django <5.0,>=2.0.4
Requires-Dist: djangorestframework <3.15,>=3.8.2
Requires-Dist: pytz >=2018.4
